dextrades-0.1.12.dist-info/METADATA
dextrades-0.1.12.dist-info/WHEEL
dextrades-0.1.12.dist-info/entry_points.txt
dextrades-0.1.12.dist-info/licenses/LICENSE
dextrades/__init__.py
dextrades/dextrades.cp312-win_amd64.pyd
dextrades_cli/__init__.py
dextrades_cli/cli.py
dextrades-0.1.12.dist-info/RECORD
