Metadata-Version: 2.4
Name: dextrades
Version: 0.1.12
Classifier: License :: OSI Approved :: MIT License
Classifier: Development Status :: 3 - Alpha
Classifier: Intended Audience :: Developers
Classifier: Programming Language :: Python
Classifier: Programming Language :: Rust
Requires-Dist: pyarrow>=15.0.0
Requires-Dist: pytest ; extra == 'dev'
Provides-Extra: dev
License-File: LICENSE
Summary: High-performance DEX swap streaming and analysis (Rust/PyO3)
Keywords: ethereum,dex,uniswap,streaming,polars,arrow,pyarrow,rust,pyo3
Author: Dextrades contributors
Requires-Python: >=3.12
Project-URL: Homepage, https://github.com/elyase/dextrades
Project-URL: Repository, https://github.com/elyase/dextrades
Project-URL: Documentation, https://github.com/elyase/dextrades#readme
